{
  "framework_metadata": {
    "framework_name": "Custom Policy Framework",
    "current_version": "1.0",
    "framework_description": "A comprehensive policy framework designed to establish governance, compliance, and operational standards for organizational activities. This framework provides structured guidance for policy development, implementation, and monitoring across various business functions.",
    "category": "General Policy Framework",
    "start_date": "2026-04-30",
    "end_date": null,
    "identifier_prefix": "POL"
  },
  "extraction_summary": {
    "total_sections_processed": 3,
    "total_policies": 223,
    "total_subpolicies": 1200,
    "policy_type_distribution": {
      "Regulatory Definition": 2,
      "Regulation": 22,
      "Definition": 5,
      "Scope": 1,
      "Interpretation": 1,
      "Regulatory Applicability": 1,
      "Disclosure Framework": 1,
      "Governance": 25,
      "Information": 1,
      "Equity": 1,
      "Stakeholder": 1,
      "Disclosure": 21,
      "Compliance": 12,
      "Operational": 2,
      "Regulatory": 4,
      "Regulatory Requirement": 35,
      "Definition Policy": 1,
      "Governance Requirement": 6,
      "Compliance Requirement": 3,
      "Disclosure Requirement": 10,
      "Reporting Obligation": 1,
      "Governance Procedure": 2,
      "Liability Framework": 1,
      "Compliance Procedure": 1,
      "Risk Management Requirement": 1,
      "Appointment Regulation": 1,
      "Insurance Regulation": 1,
      "Obligations Regulation": 1,
      "Corporate Governance Regulation": 1,
      "Succession Regulation": 1,
      "Reporting Requirement": 4,
      "Approval Requirement": 1,
      "Notification Requirement": 2,
      "Agreement Disclosure": 1,
      "Shareholding Disclosure": 1,
      "Corporate Governance": 1,
      "Procedural": 1,
      "Financial Reporting": 2,
      "Governance/Compliance": 1,
      "Regulatory Disclosure": 2,
      "Regulatory Scope": 2,
      "Event Disclosure": 3,
      "Regulatory Disclosure Requirement": 1,
      "Security Requirement": 1,
      "Rating Requirement": 1,
      "Trustee Communication Requirement": 1,
      "Compensation": 1,
      "Reporting": 3,
      "Compliance Obligation": 1,
      "Regulatory Obligation": 2,
      "Disclosure Obligation": 1,
      "Valuation Requirement": 1,
      "Security Terms": 1,
      "Record Date Procedure": 1,
      "Dissemination Requirement": 1,
      "Operational Requirement": 1,
      "Procedure Requirement": 2,
      "Exemption Policy": 1,
      "Regulatory Power": 1,
      "Regulatory Compliance": 2,
      "Audit Disclosure": 1,
      "Communication": 1,
      "Information Disclosure": 1,
      "Compliance / Disclosure Requirement": 1,
      "Policy": 2,
      "Regulatory Amendment": 2,
      "Regulatory amendment": 3,
      "Regulatory Policy": 1,
      "Regulatory Framework": 1
    },
    "api_calls_made": 5,
    "extraction_date": "2026-04-30T13:49:38.968395"
  }
}