{
  "framework_metadata": {
    "framework_name": "Custom Policy Framework",
    "current_version": "1.0",
    "framework_description": "A comprehensive policy framework designed to establish governance, compliance, and operational standards for organizational activities. This framework provides structured guidance for policy development, implementation, and monitoring across various business functions.",
    "category": "General Policy Framework",
    "start_date": "2026-01-08",
    "end_date": null,
    "identifier_prefix": "POL"
  },
  "extraction_summary": {
    "total_sections_processed": 3,
    "total_policies": 4,
    "total_subpolicies": 8,
    "policy_type_distribution": {
      "Security": 4
    },
    "api_calls_made": 3,
    "extraction_date": "2026-01-08T17:15:21.545094"
  }
}